{
    "desktop": [
        {
            "name": "Wall301",
            "url": "https://raw.githubusercontent.com/saumil8200/canva-walls/main/desktop/Wall301.png"
        },
        {
            "name": "Wall304",
            "url": "https://raw.githubusercontent.com/saumil8200/canva-walls/main/desktop/Wall304.png"
        }
    ],
    "mobile": [
        {
            "name": "Wall302",
            "url": "https://raw.githubusercontent.com/saumil8200/canva-walls/main/mobile/Wall302.png"
        },
        {
            "name": "Wall303",
            "url": "https://raw.githubusercontent.com/saumil8200/canva-walls/main/mobile/Wall303.png"
        }
    ],
    "compressed_desktop": [
        {
            "name": "Wall301",
            "url": "https://raw.githubusercontent.com/saumil8200/canva-walls/main/compressed_desktop/Wall301.png"
        },
        {
            "name": "Wall304",
            "url": "https://raw.githubusercontent.com/saumil8200/canva-walls/main/compressed_desktop/Wall304.png"
        }
    ],
    "compressed_mobile": [
        {
            "name": "Wall302",
            "url": "https://raw.githubusercontent.com/saumil8200/canva-walls/main/compressed_mobile/Wall302.png"
        },
        {
            "name": "Wall303",
            "url": "https://raw.githubusercontent.com/saumil8200/canva-walls/main/compressed_mobile/Wall303.png"
        }
    ]
}